[
    {
      "_id": "5a1050007b3918408bab8849",
      "isActive": true,
      "picture": "/images/placeholder.png",
      "age": 20,
      "name": "Grace Henson"
    },
    {
      "_id": "5a105000b71ae4a60775b034",
      "isActive": true,
      "picture": "/images/placeholder.png",
      "age": 29,
      "name": "Antonia Nieves"
    },
    {
      "_id": "5a105000060412977ae99cea",
      "isActive": false,
      "picture": "/images/placeholder.png",
      "age": 35,
      "name": "Nunez Kim"
    },
    {
      "_id": "5a105000dba91323c800136e",
      "isActive": false,
      "picture": "/images/placeholder.png",
      "age": 30,
      "name": "Johanna Brock"
    },
    {
      "_id": "5a1050007265bff0db9076b0",
      "isActive": true,
      "picture": "/images/placeholder.png",
      "age": 26,
      "name": "Ellison Ford"
    },
    {
      "_id": "5a105000950d41f55ab59503",
      "isActive": false,
      "picture": "/images/placeholder.png",
      "age": 20,
      "name": "Cora Mckay"
    },
    {
      "_id": "5a105000c5d69f99648d05ff",
      "isActive": false,
      "picture": "/images/placeholder.png",
      "age": 37,
      "name": "Rosie Cannon"
    },
    {
      "_id": "5a105000f6f78f3110ce52b4",
      "isActive": false,
      "picture": "/images/placeholder.png",
      "age": 21,
      "name": "Tate Dillon"
    },
    {
      "_id": "5a105000a71f67eddaae7c62",
      "isActive": true,
      "picture": "/images/placeholder.png",
      "age": 25,
      "name": "Swanson Chaney"
    },
    {
      "_id": "5a1050004c5049171d75925a",
      "isActive": false,
      "picture": "/images/placeholder.png",
      "age": 39,
      "name": "Claudette Hill"
    },
    {
      "_id": "5a10500014e9c739b31827ae",
      "isActive": false,
      "picture": "/images/placeholder.png",
      "age": 31,
      "name": "Freeman Page"
    },
    {
      "_id": "5a105000f4dadd9962086f19",
      "isActive": true,
      "picture": "/images/placeholder.png",
      "age": 28,
      "name": "Willis Cabrera"
    },
    {
      "_id": "5a10500057db2d14c886da5f",
      "isActive": false,
      "picture": "/images/placeholder.png",
      "age": 29,
      "name": "Fitzgerald Vang"
    },
    {
      "_id": "5a105000532dba97dcda5a09",
      "isActive": true,
      "picture": "/images/placeholder.png",
      "age": 37,
      "name": "Ratliff Middleton"
    },
    {
      "_id": "5a1050008300728fda49f4f5",
      "isActive": false,
      "picture": "/images/placeholder.png",
      "age": 29,
      "name": "Wendi Sherman"
    },
    {
      "_id": "5a105000cad5cccaa0e9fc88",
      "isActive": false,
      "picture": "/images/placeholder.png",
      "age": 21,
      "name": "Schultz Rowland"
    },
    {
      "_id": "5a1050008c294ef2e9f6d7a3",
      "isActive": false,
      "picture": "/images/placeholder.png",
      "age": 39,
      "name": "Morrow Solomon"
    },
    {
      "_id": "5a10500017e5c126c51397fb",
      "isActive": false,
      "picture": "/images/placeholder.png",
      "age": 25,
      "name": "Obrien Guthrie"
    },
    {
      "_id": "5a105000fb899c780e57ebc8",
      "isActive": false,
      "picture": "/images/placeholder.png",
      "age": 40,
      "name": "Meyers Lester"
    },
    {
      "_id": "5a1050000ff3bb733d6e2db0",
      "isActive": true,
      "picture": "/images/placeholder.png",
      "age": 24,
      "name": "Renee Gallagher"
    },
    {
      "_id": "5a105000707b5127d99f3eae",
      "isActive": false,
      "picture": "/images/placeholder.png",
      "age": 24,
      "name": "Harriet Curry"
    },
    {
      "_id": "5a1050009911f18780a7aacf",
      "isActive": false,
      "picture": "/images/placeholder.png",
      "age": 38,
      "name": "Brennan Clayton"
    },
    {
      "_id": "5a10500002073f60c1089fc8",
      "isActive": true,
      "picture": "/images/placeholder.png",
      "age": 38,
      "name": "Georgina Flynn"
    },
    {
      "_id": "5a1050000bfe3770a8b3fcf3",
      "isActive": true,
      "picture": "/images/placeholder.png",
      "age": 28,
      "name": "Simpson Gardner"
    },
    {
      "_id": "5a1050001346682c89a54f68",
      "isActive": true,
      "picture": "/images/placeholder.png",
      "age": 25,
      "name": "Sabrina Webster"
    },
    {
      "_id": "5a10500063031eb474529ca5",
      "isActive": false,
      "picture": "/images/placeholder.png",
      "age": 22,
      "name": "Carissa Blake"
    },
    {
      "_id": "5a105000309fe0ba847ce369",
      "isActive": true,
      "picture": "/images/placeholder.png",
      "age": 37,
      "name": "Salazar Hart"
    },
    {
      "_id": "5a1050007035c2eb8c9fa606",
      "isActive": true,
      "picture": "/images/placeholder.png",
      "age": 38,
      "name": "Anne Leblanc"
    },
    {
      "_id": "5a1050002da03183a27bf703",
      "isActive": false,
      "picture": "/images/placeholder.png",
      "age": 28,
      "name": "Benton Dickson"
    },
    {
      "_id": "5a105000aa0930b7bae35f15",
      "isActive": false,
      "picture": "/images/placeholder.png",
      "age": 34,
      "name": "Vaughan Levine"
    },
    {
      "_id": "5a105000fc7ea7298ac8ab70",
      "isActive": false,
      "picture": "/images/placeholder.png",
      "age": 38,
      "name": "Vinson Nelson"
    },
    {
      "_id": "5a1050001e275b4fa0a8b3f9",
      "isActive": false,
      "picture": "/images/placeholder.png",
      "age": 21,
      "name": "Wiggins Weber"
    },
    {
      "_id": "5a105000472fd41b5a74fb64",
      "isActive": false,
      "picture": "/images/placeholder.png",
      "age": 25,
      "name": "Combs Pearson"
    },
    {
      "_id": "5a10500029db195c35cbc691",
      "isActive": false,
      "picture": "/images/placeholder.png",
      "age": 32,
      "name": "Shanna Dunlap"
    },
    {
      "_id": "5a1050009889895a6d40f424",
      "isActive": false,
      "picture": "/images/placeholder.png",
      "age": 33,
      "name": "Robert Hunt"
    },
    {
      "_id": "5a10500076acee0540fe0784",
      "isActive": true,
      "picture": "/images/placeholder.png",
      "age": 40,
      "name": "Stokes Fernandez"
    },
    {
      "_id": "5a105000e60fbf9e1abea393",
      "isActive": true,
      "picture": "/images/placeholder.png",
      "age": 20,
      "name": "Lenora Odonnell"
    },
    {
      "_id": "5a105000c00817e1d6b02b8c",
      "isActive": false,
      "picture": "/images/placeholder.png",
      "age": 25,
      "name": "Huffman Golden"
    },
    {
      "_id": "5a105000e48ca3cc8319b5dd",
      "isActive": true,
      "picture": "/images/placeholder.png",
      "age": 40,
      "name": "Bonita Blair"
    },
    {
      "_id": "5a105000d13d2987786c5611",
      "isActive": true,
      "picture": "/images/placeholder.png",
      "age": 30,
      "name": "Morales Buckner"
    },
    {
      "_id": "5a1050001e7536c36df0c6c2",
      "isActive": true,
      "picture": "/images/placeholder.png",
      "age": 22,
      "name": "Marsh Hopkins"
    },
    {
      "_id": "5a105000547069652d6c63f7",
      "isActive": true,
      "picture": "/images/placeholder.png",
      "age": 37,
      "name": "Dana Maxwell"
    },
    {
      "_id": "5a105000d12f798accc4c7b9",
      "isActive": false,
      "picture": "/images/placeholder.png",
      "age": 24,
      "name": "Adela Mckinney"
    },
    {
      "_id": "5a10500011860c032b401e6e",
      "isActive": false,
      "picture": "/images/placeholder.png",
      "age": 31,
      "name": "Barrera Holden"
    },
    {
      "_id": "5a105000425f56a5575377df",
      "isActive": true,
      "picture": "/images/placeholder.png",
      "age": 28,
      "name": "Edwards Willis"
    },
    {
      "_id": "5a10500011fc1115340e3c78",
      "isActive": false,
      "picture": "/images/placeholder.png",
      "age": 24,
      "name": "Rosalind Gates"
    },
    {
      "_id": "5a1050004d809234a175cdb0",
      "isActive": false,
      "picture": "/images/placeholder.png",
      "age": 32,
      "name": "Gomez Lyons"
    },
    {
      "_id": "5a105000136013bf869fd687",
      "isActive": true,
      "picture": "/images/placeholder.png",
      "age": 22,
      "name": "Roxie Talley"
    },
    {
      "_id": "5a1050003690ebaa2d62c74c",
      "isActive": false,
      "picture": "/images/placeholder.png",
      "age": 26,
      "name": "Nicole Nielsen"
    },
    {
      "_id": "5a1050006316824b6e22b960",
      "isActive": true,
      "picture": "/images/placeholder.png",
      "age": 20,
      "name": "Kim Barnes"
    },
    {
      "_id": "5a105000488eb71d44af80db",
      "isActive": true,
      "picture": "/images/placeholder.png",
      "age": 23,
      "name": "Wood Green"
    },
    {
      "_id": "5a1050007a8a4579596cba46",
      "isActive": true,
      "picture": "/images/placeholder.png",
      "age": 31,
      "name": "Wiley Dotson"
    },
    {
      "_id": "5a1050000a8e552e7c5d1c32",
      "isActive": false,
      "picture": "/images/placeholder.png",
      "age": 37,
      "name": "Gretchen Vargas"
    }
  ]